{"$schema": "http://cyclonedx.org/schema/bom-1.4.schema.json", "bomFormat": "CycloneDX", "specVersion": "1.4", "serialNumber": "urn:uuid:82677c0c-beaa-4de7-b60e-245d89feb4fc", "version": 1, "metadata": {"timestamp": "2022-11-17T01:49:30.000358+00:00", "tools": [{"vendor": "CycloneDX", "name": "cyclonedx-bom", "version": "3.7.2"}, {"vendor": "CycloneDX", "name": "cyclonedx-python-lib", "version": "3.1.0", "externalReferences": [{"url": "https://github.com/CycloneDX/cyclonedx-python-lib/actions", "type": "build-system"}, {"url": "https://pypi.org/project/cyclonedx-python-lib/", "type": "distribution"}, {"url": "https://cyclonedx.github.io/cyclonedx-python-lib/", "type": "documentation"}, {"url": "https://github.com/CycloneDX/cyclonedx-python-lib/issues", "type": "issue-tracker"}, {"url": "https://github.com/CycloneDX/cyclonedx-python-lib/blob/main/LICENSE", "type": "license"}, {"url": "https://github.com/CycloneDX/cyclonedx-python-lib/blob/main/CHANGELOG.md", "type": "release-notes"}, {"url": "https://github.com/CycloneDX/cyclonedx-python-lib", "type": "vcs"}, {"url": "https://cyclonedx.org", "type": "website"}]}]}, "components": [{"type": "library", "bom-ref": "aacfdf54-3b7f-492e-adf7-ad5c44d583fc", "name": "CacheControl", "version": "0.12.6", "purl": "pkg:pypi/cachecontrol@0.12.6"}, {"type": "library", "bom-ref": "2102a430-58c7-4830-acad-b2ff035b1200", "name": "Pillow", "version": "8.3.2", "purl": "pkg:pypi/pillow@8.3.2"}, {"type": "library", "bom-ref": "5af0a09a-f74c-4165-b66f-2555786a9e9c", "name": "appdirs", "version": "1.4.3", "purl": "pkg:pypi/appdirs@1.4.3"}, {"type": "library", "bom-ref": "d6008ce8-0490-4099-bd60-af73915ae6bc", "name": "beautifulsoup4", "version": "4.9.2", "purl": "pkg:pypi/beautifulsoup4@4.9.2"}, {"type": "library", "bom-ref": "89832f61-5b40-4708-b815-4d4111978651", "name": "bs4", "version": "0.0.1", "purl": "pkg:pypi/bs4@0.0.1"}, {"type": "library", "bom-ref": "58873c13-5c5e-493c-8663-6ad90f9dd5db", "name": "certifi", "version": "2019.11.28", "purl": "pkg:pypi/certifi@2019.11.28"}, {"type": "library", "bom-ref": "f2f8a631-349e-42f5-810f-c5fe33561d1f", "name": "chardet", "version": "3.0.4", "purl": "pkg:pypi/chardet@3.0.4"}, {"type": "library", "bom-ref": "4c12b65a-f17b-4be6-91ba-a840b546786c", "name": "colorama", "version": "0.4.3", "purl": "pkg:pypi/colorama@0.4.3"}, {"type": "library", "bom-ref": "037fa96a-7460-400b-b6d5-21153d073431", "name": "contextlib2", "version": "0.6.0", "purl": "pkg:pypi/contextlib2@0.6.0"}, {"type": "library", "bom-ref": "27a926d9-b6fd-48c7-87cf-a059d1d88e71", "name": "distlib", "version": "0.3.0", "purl": "pkg:pypi/distlib@0.3.0"}, {"type": "library", "bom-ref": "34c23fc9-b7bb-4ced-bb93-f03205ab79e8", "name": "distro", "version": "1.4.0", "purl": "pkg:pypi/distro@1.4.0"}, {"type": "library", "bom-ref": "b31b6982-93d4-4a6e-81d1-b6202c8fdf45", "name": "html5lib", "version": "1.0.1", "purl": "pkg:pypi/html5lib@1.0.1"}, {"type": "library", "bom-ref": "9dd907f6-5efc-4c3f-b16d-ef5d57eb04e2", "name": "idna", "version": "2.8", "purl": "pkg:pypi/idna@2.8"}, {"type": "library", "bom-ref": "67d20d06-21a9-4761-b2c1-4e9b2a1b99bd", "name": "ipaddr", "version": "2.2.0", "purl": "pkg:pypi/ipaddr@2.2.0"}, {"type": "library", "bom-ref": "8b226172-0a1f-49fd-8aed-735c22a13d73", "name": "lockfile", "version": "0.12.2", "purl": "pkg:pypi/lockfile@0.12.2"}, {"type": "library", "bom-ref": "a6baa67d-2ad4-4482-9cdb-dba8a4f45d21", "name": "lxml", "version": "4.6.3", "purl": "pkg:pypi/lxml@4.6.3"}, {"type": "library", "bom-ref": "efb7c05d-7597-4cd1-8662-5894e1fc4332", "name": "msgpack", "version": "0.6.2", "purl": "pkg:pypi/msgpack@0.6.2"}, {"type": "library", "bom-ref": "dde84ce5-99aa-4465-91f1-97812c1e1cc1", "name": "packaging", "version": "20.3", "purl": "pkg:pypi/packaging@20.3"}, {"type": "library", "bom-ref": "3c84a250-e35b-4ce2-b8ae-9ad23fee1c70", "name": "pep517", "version": "0.8.2", "purl": "pkg:pypi/pep517@0.8.2"}, {"type": "library", "bom-ref": "63afadd3-0058-46da-a580-3fc57f700127", "name": "progress", "version": "1.5", "purl": "pkg:pypi/progress@1.5"}, {"type": "library", "bom-ref": "c3e4db41-82f7-4f0c-8840-dc1075fb1204", "name": "pyparsing", "version": "2.4.6", "purl": "pkg:pypi/pyparsing@2.4.6"}, {"type": "library", "bom-ref": "376dbfb3-0add-4138-8730-207b2fd8bd36", "name": "pytoml", "version": "0.1.21", "purl": "pkg:pypi/pytoml@0.1.21"}, {"type": "library", "bom-ref": "07581995-08f1-4db2-b077-8e71629eae68", "name": "requests", "version": "2.28.1", "purl": "pkg:pypi/requests@2.28.1"}, {"type": "library", "bom-ref": "dcc3fff5-13ee-45f2-9489-35afe533b08d", "name": "retrying", "version": "1.3.3", "purl": "pkg:pypi/retrying@1.3.3"}, {"type": "library", "bom-ref": "360f9454-f510-4ae1-b9cc-091f1ac6681a", "name": "six", "version": "1.14.0", "purl": "pkg:pypi/six@1.14.0"}, {"type": "library", "bom-ref": "4d1fdfaa-efeb-43db-a051-751cf763365a", "name": "soupsieve", "version": "2.0.1", "purl": "pkg:pypi/soupsieve@2.0.1"}, {"type": "library", "bom-ref": "a5201ef3-df82-4fce-b14e-165faab95094", "name": "tqdm", "version": "4.50.0", "purl": "pkg:pypi/tqdm@4.50.0"}, {"type": "library", "bom-ref": "37f7e9a5-83c0-47ae-807b-b11429b27ab5", "name": "urllib3", "version": "1.26.12", "purl": "pkg:pypi/urllib3@1.26.12"}, {"type": "library", "bom-ref": "49813d93-3cea-4bc9-b5e0-9b6cf7679d52", "name": "webencodings", "version": "0.5.1", "purl": "pkg:pypi/webencodings@0.5.1"}], "dependencies": [{"ref": "aacfdf54-3b7f-492e-adf7-ad5c44d583fc", "dependsOn": []}, {"ref": "2102a430-58c7-4830-acad-b2ff035b1200", "dependsOn": []}, {"ref": "5af0a09a-f74c-4165-b66f-2555786a9e9c", "dependsOn": []}, {"ref": "d6008ce8-0490-4099-bd60-af73915ae6bc", "dependsOn": []}, {"ref": "89832f61-5b40-4708-b815-4d4111978651", "dependsOn": []}, {"ref": "58873c13-5c5e-493c-8663-6ad90f9dd5db", "dependsOn": []}, {"ref": "f2f8a631-349e-42f5-810f-c5fe33561d1f", "dependsOn": []}, {"ref": "4c12b65a-f17b-4be6-91ba-a840b546786c", "dependsOn": []}, {"ref": "037fa96a-7460-400b-b6d5-21153d073431", "dependsOn": []}, {"ref": "27a926d9-b6fd-48c7-87cf-a059d1d88e71", "dependsOn": []}, {"ref": "34c23fc9-b7bb-4ced-bb93-f03205ab79e8", "dependsOn": []}, {"ref": "b31b6982-93d4-4a6e-81d1-b6202c8fdf45", "dependsOn": []}, {"ref": "9dd907f6-5efc-4c3f-b16d-ef5d57eb04e2", "dependsOn": []}, {"ref": "67d20d06-21a9-4761-b2c1-4e9b2a1b99bd", "dependsOn": []}, {"ref": "8b226172-0a1f-49fd-8aed-735c22a13d73", "dependsOn": []}, {"ref": "a6baa67d-2ad4-4482-9cdb-dba8a4f45d21", "dependsOn": []}, {"ref": "efb7c05d-7597-4cd1-8662-5894e1fc4332", "dependsOn": []}, {"ref": "dde84ce5-99aa-4465-91f1-97812c1e1cc1", "dependsOn": []}, {"ref": "3c84a250-e35b-4ce2-b8ae-9ad23fee1c70", "dependsOn": []}, {"ref": "63afadd3-0058-46da-a580-3fc57f700127", "dependsOn": []}, {"ref": "c3e4db41-82f7-4f0c-8840-dc1075fb1204", "dependsOn": []}, {"ref": "376dbfb3-0add-4138-8730-207b2fd8bd36", "dependsOn": []}, {"ref": "07581995-08f1-4db2-b077-8e71629eae68", "dependsOn": []}, {"ref": "dcc3fff5-13ee-45f2-9489-35afe533b08d", "dependsOn": []}, {"ref": "360f9454-f510-4ae1-b9cc-091f1ac6681a", "dependsOn": []}, {"ref": "4d1fdfaa-efeb-43db-a051-751cf763365a", "dependsOn": []}, {"ref": "a5201ef3-df82-4fce-b14e-165faab95094", "dependsOn": []}, {"ref": "37f7e9a5-83c0-47ae-807b-b11429b27ab5", "dependsOn": []}, {"ref": "49813d93-3cea-4bc9-b5e0-9b6cf7679d52", "dependsOn": []}]}